MANIFEST.in
README.md
setup.py
bin/meerkathi
meerkathi/__init__.py
meerkathi/default-config.yml
meerkathi.egg-info/PKG-INFO
meerkathi.egg-info/SOURCES.txt
meerkathi.egg-info/dependency_links.txt
meerkathi.egg-info/requires.txt
meerkathi.egg-info/top_level.txt
meerkathi/data/casa_calibrators.yml
meerkathi/data/southern_calibrators.txt
meerkathi/dispatch_crew/__init__.py
meerkathi/dispatch_crew/caltables.py
meerkathi/dispatch_crew/catalog_parser.py
meerkathi/dispatch_crew/config_parser.py
meerkathi/dispatch_crew/meerkat_archive_interface.py
meerkathi/dispatch_crew/reporter.py
meerkathi/dispatch_crew/utils.py
meerkathi/scripts/__init__.py
meerkathi/scripts/conf_helper/index.html
meerkathi/scripts/conf_helper/css/default.css
meerkathi/scripts/conf_helper/javascript/model_parameterfile.js
meerkathi/scripts/conf_helper/javascript/viewer_consoleviewer.js
meerkathi/scripts/conf_helper/javascript/viewer_fieldeditor.js
meerkathi/scripts/conf_helper/javascript/viewer_outline.js
meerkathi/scripts/conf_helper/javascript/js-yaml/.editorconfig
meerkathi/scripts/conf_helper/javascript/js-yaml/.eslintignore
meerkathi/scripts/conf_helper/javascript/js-yaml/.eslintrc.yml
meerkathi/scripts/conf_helper/javascript/js-yaml/.git
meerkathi/scripts/conf_helper/javascript/js-yaml/.gitignore
meerkathi/scripts/conf_helper/javascript/js-yaml/.ndocrc
meerkathi/scripts/conf_helper/javascript/js-yaml/.travis.yml
meerkathi/scripts/conf_helper/javascript/js-yaml/CHANGELOG.md
meerkathi/scripts/conf_helper/javascript/js-yaml/LICENSE
meerkathi/scripts/conf_helper/javascript/js-yaml/Makefile
meerkathi/scripts/conf_helper/javascript/js-yaml/README.md
meerkathi/scripts/conf_helper/javascript/js-yaml/bower.json
meerkathi/scripts/conf_helper/javascript/js-yaml/index.js
meerkathi/scripts/conf_helper/javascript/js-yaml/package.json
meerkathi/scripts/conf_helper/javascript/js-yaml/benchmark/add-by-tag.sh
meerkathi/scripts/conf_helper/javascript/js-yaml/benchmark/benchmark.js
meerkathi/scripts/conf_helper/javascript/js-yaml/benchmark/profile.js
meerkathi/scripts/conf_helper/javascript/js-yaml/benchmark/implementations/current/index.js
