Metadata-Version: 1.1
Name: meerkathi
Version: 0.1.0
Summary: MeerKAT end-to-end data reduction pipeline
Home-page: https://github.com/sphemakh/meerkathi
Author: MeerKATHI peeps
Author-email: sphemakh@gmail.com
License: ['GNU GPL v2']
Platform: UNKNOWN
Classifier: Development Status :: 3 - Alpha
Classifier: Intended Audience :: Science/Research
Classifier: License :: OSI Approved :: GNU General Public License v2 (GPLv2)
Classifier: Operating System :: POSIX :: Linux
Classifier: Programming Language :: Python
Classifier: Topic :: Scientific/Engineering :: Astronomy
